__init__.py
aliprocessing/__init__.py
aliprocessing/_version.py
aliprocessing/core/__init__.py
aliprocessing/core/instrument/__init__.py
aliprocessing/data/retrieval/aerosol_apriori.txt
aliprocessing/l1b/__init__.py
aliprocessing/l1b/data.py
aliprocessing/l2/__init__.py
aliprocessing/legacy/__init__.py
aliprocessing/legacy/instrument/__init__.py
aliprocessing/legacy/instrument/aotf.py
aliprocessing/legacy/instrument/lcr.py
aliprocessing/legacy/instrument/lenses.py
aliprocessing/legacy/instrument/lineshape.py
aliprocessing/legacy/instrument/polarizer.py
aliprocessing/legacy/instrument/sensor.py
aliprocessing/legacy/instrument/sensor_2channel.py
aliprocessing/legacy/instrument/simulator.py
aliprocessing/legacy/instrument/spectralimager.py
aliprocessing/legacy/instrument/data/Aluminum_Coating_Comparison_Data.xlsx
aliprocessing/legacy/instrument/data/aluminum_coating_thorlab.txt
aliprocessing/legacy/instrument/data/gold_coating_mirror_aoi12.txt
aliprocessing/legacy/instrument/data/gold_coating_mirror_aoi45.txt
aliprocessing/legacy/instrument/sensors/__init__.py
aliprocessing/legacy/instrument/sensors/base_sensor.py
aliprocessing/legacy/instrument/sensors/cardinal_1280.py
aliprocessing/legacy/instrument/sensors/cardinal_640.py
aliprocessing/legacy/instrument/sensors/raptor_owl_640_n.py
aliprocessing/legacy/instrument/sensors/teledyne_ccd97.py
aliprocessing/legacy/retrieval/__init__.py
aliprocessing/legacy/retrieval/aerosol.py
aliprocessing/legacy/retrieval/cloud.py
aliprocessing/legacy/retrieval/extinction.py
aliprocessing/legacy/retrieval/particlesize.py
aliprocessing/legacy/retrieval/statevector.py
aliprocessing/legacy/retrieval/measvec/__init__.py
aliprocessing/legacy/retrieval/measvec/transformer.py
aliprocessing/legacy/util/__init__.py
aliprocessing/legacy/util/aerosol.py
aliprocessing/legacy/util/analysis.py
aliprocessing/legacy/util/atmospheres.py
aliprocessing/legacy/util/config.py
aliprocessing/legacy/util/er2.py
aliprocessing/legacy/util/geometry.py
aliprocessing-2025.1.0.dist-info/LICENSE
aliprocessing-2025.1.0.dist-info/METADATA
aliprocessing-2025.1.0.dist-info/WHEEL
aliprocessing-2025.1.0.dist-info/top_level.txt
aliprocessing-2025.1.0.dist-info/RECORD
