Metadata-Version: 2.2
Name: aliprocessing
Version: 2025.1.0
Summary: Aerosol Limb Imager processing code
Author-email: Landon Rieger <landon.rieger@usask.ca>, Daniel Zawada <daniel.zawada@usask.ca>
Classifier: Development Status :: 4 - Beta
Classifier: Programming Language :: Python :: 3 :: Only
Classifier: Programming Language :: Python :: 3.11
Classifier: Programming Language :: Python :: 3.12
Classifier: Programming Language :: Python :: 3.13
Requires-Python: >=3.11
License-File: LICENSE
Requires-Dist: numpy
Requires-Dist: skretrieval
Provides-Extra: test
Requires-Dist: pytest; extra == "test"
Provides-Extra: plotting
Requires-Dist: matplotlib; extra == "plotting"
